---
id: å…³äºbyte b+=1å’Œb=b+1çš„é—®é¢˜
title: ğŸ¬byte b += 1 å’Œ b = b + 1
---
import ImgBox from "../../src/components/ImgBox";

å…ˆæ¥çœ‹ä¸‹é—®é¢˜ï¼Œå¦‚ä¸‹å›¾ã€‚å£°æ˜äº†ä¸€ä¸ªå˜é‡ `byte b = 100;`ï¼Œç¬¬5è¡Œä»£ç ç¼–è¯‘æ­£å¸¸ï¼Œç¬¬6è¡Œä»£ç ç¼–è¯‘å™¨æŠ¥é”™ã€‚

<ImgBox src="https://upyun1.surcode.cn/imgs/20220512234622.png" />

åŸå› æ˜¯ï¼ŒJavaç¼–è¯‘å™¨åœ¨å¤„ç† `+=` æ—¶ï¼Œä¼šè‡ªåŠ¨è¿›è¡Œå¼ºè½¬ï¼ˆçª„åŒ–å¤„ç†ï¼‰ï¼Œè¿™å±äºä¸€ä¸ªJavaçš„è¯­æ³•ç³–ã€‚

ä¸‹é¢æ˜¯åç¼–è¯‘çš„å­—èŠ‚ç æŒ‡ä»¤ï¼š

```
$ javap -v -l Hello
Classfile /Users/liyan/Documents/java-class/learning-java/src/Hello.class
  Last modified 2022-5-12; size 271 bytes
  MD5 checksum d656ead69e7ab2b5502aa1530196ce9f
  Compiled from "Hello.java"
public class Hello
  minor version: 0
  major version: 52
  flags: ACC_PUBLIC, ACC_SUPER
Constant pool:
   #1 = Methodref          #3.#12         // java/lang/Object."<init>":()V
   #2 = Class              #13            // Hello
   #3 = Class              #14            // java/lang/Object
   #4 = Utf8               <init>
   #5 = Utf8               ()V
   #6 = Utf8               Code
   #7 = Utf8               LineNumberTable
   #8 = Utf8               main
   #9 = Utf8               ([Ljava/lang/String;)V
  #10 = Utf8               SourceFile
  #11 = Utf8               Hello.java
  #12 = NameAndType        #4:#5          // "<init>":()V
  #13 = Utf8               Hello
  #14 = Utf8               java/lang/Object
{
  public Hello();
    descriptor: ()V
    flags: ACC_PUBLIC
    Code:
      stack=1, locals=1, args_size=1
         0: aload_0
         1: invokespecial #1                  // Method java/lang/Object."<init>":()V
         4: return
      LineNumberTable:
        line 1: 0

  public static void main(java.lang.String[]);
    descriptor: ([Ljava/lang/String;)V
    flags: ACC_PUBLIC, ACC_STATIC
    Code:
      stack=2, locals=2, args_size=1
         0: bipush        100
         2: istore_1
         3: iload_1
         4: iconst_1
         5: iadd
         6: i2b
         7: istore_1
         8: return
      LineNumberTable:
        line 4: 0
        line 5: 3
        line 6: 8
}
SourceFile: "Hello.java"
```